cellspat/__init__.py
cellspat/cellspat_run.py
cellspat-0.0.2.dist-info/LICENSE
cellspat-0.0.2.dist-info/METADATA
cellspat-0.0.2.dist-info/WHEEL
cellspat-0.0.2.dist-info/top_level.txt
cellspat-0.0.2.dist-info/RECORD
