Metadata-Version: 2.1
Name: cellspat
Version: 0.0.2
Summary: cell-cell communcation tools for spatial transcriptomics
Author-email: Varsha Sreekanth <vsreek3@uic.edu>
Project-URL: Homepage, https://github.com/jaleesr/cellSpat
Project-URL: Bug Tracker, https://github.com/jaleesr/cellSpat
Classifier: Programming Language :: Python :: 3
Classifier: License :: OSI Approved :: MIT License
Classifier: Operating System :: OS Independent
Requires-Python: >=3.9
License-File: LICENSE
Requires-Dist: numpy >=2.0.2
Requires-Dist: pandas >=2.3.1
Requires-Dist: esda >=2.5.1
Requires-Dist: scipy >=1.13.1
Requires-Dist: statsmodels >=0.14.5
Requires-Dist: geopandas >=1.0.1
Requires-Dist: shapely >=2.0.7
Requires-Dist: libpysal >=4.7.0
Provides-Extra: scdrs
Requires-Dist: scanpy >=1.10.3 ; extra == 'scdrs'
